stdeb/__init__.py
stdeb/cli_runner.py
stdeb/downloader.py
stdeb/pypi_simple.py
stdeb/transport.py
stdeb/util.py
stdeb/which.py
stdeb/command/__init__.py
stdeb/command/bdist_deb.py
stdeb/command/common.py
stdeb/command/debianize.py
stdeb/command/install_deb.py
stdeb/command/sdist_dsc.py
stdeb-0.10.2.data/scripts/py2dsc
stdeb-0.10.2.data/scripts/py2dsc-deb
stdeb-0.10.2.data/scripts/pypi-download
stdeb-0.10.2.data/scripts/pypi-install
stdeb-0.10.2.dist-info/LICENSE.txt
stdeb-0.10.2.dist-info/METADATA
stdeb-0.10.2.dist-info/WHEEL
stdeb-0.10.2.dist-info/top_level.txt
stdeb-0.10.2.dist-info/RECORD
