Metadata-Version: 2.1
Name: stdeb
Version: 0.10.2
Summary: Python to Debian source package conversion utility
Home-page: http://github.com/astraw/stdeb
Author: Andrew Straw
Author-email: strawman@astraw.com
License: MIT
Classifier: Development Status :: 5 - Production/Stable
Classifier: Intended Audience :: Developers
Classifier: Intended Audience :: System Administrators
Classifier: License :: OSI Approved :: MIT License
Classifier: Operating System :: POSIX :: Linux
Classifier: Programming Language :: Python :: 2.7
Classifier: Programming Language :: Python :: 3
License-File: LICENSE.txt
